upstash_redis/__init__.py
upstash_redis/asyncio/__init__.py
upstash_redis/asyncio/client.py
upstash_redis/config.py
upstash_redis/exception.py
upstash_redis/http/decode.py
upstash_redis/http/execute.py
upstash_redis/py.typed
upstash_redis/schema/commands/parameters.py
upstash_redis/schema/commands/returns.py
upstash_redis/schema/http.py
upstash_redis/schema/telemetry.py
upstash_redis/utils/base.py
upstash_redis/utils/comparison.py
upstash_redis/utils/exception.py
upstash_redis/utils/format.py
upstash_redis_a-0.1.14.dist-info/LICENSE
upstash_redis_a-0.1.14.dist-info/METADATA
upstash_redis_a-0.1.14.dist-info/WHEEL
upstash_redis_a-0.1.14.dist-info/RECORD
